{
    "党课":
    {
        "channel":
        [
         {
         "listUrl":
         "http://roll.qiushi.chinaso.com/newsQuery/query/getNewsList.htm?channel=&queryId=334&subChannel=&tableName=studyaction&tableId=table_110&date=&day=&pageSize=20&type=abstract&sourceType=0,1,2,3,4,5&IsRoll=0,1",
         "name":
         "课程1"
         },
         {
         "listUrl":
         "http://roll.qiushi.chinaso.com/newsQuery/query/getNewsList.htm?channel=&queryId=336&subChannel=&tableName=studyaction&tableId=table_110&date=&day=&pageSize=20&type=abstract&sourceType=0,1,2,3,4,5&IsRoll=0,1",
         "name":
         "不限"
         },
         {
         "listUrl":
         "http://roll.qiushi.chinaso.com/newsQuery/query/getNewsList.htm?channel=&queryId=338&subChannel=&tableName=studyaction&tableId=table_110&date=&day=&pageSize=20&type=abstract&sourceType=0,1,2,3,4,5&IsRoll=0,1",
         "name":
         "求是访谈"
         },
         {
         "listUrl":
         "http://roll.qiushi.chinaso.com/newsQuery/query/getNewsList.htm?channel=&queryId=340&subChannel=&tableName=studyaction&tableId=table_110&date=&day=&pageSize=20&type=abstract&sourceType=0,1,2,3,4,5&IsRoll=0,1",
         "name":
         "微访谈"
         }
         ],
        "focusUrl":
        "http://roll.qiushi.chinaso.com/newsQuery/query/getNewsList.htm?channel=&queryId=332&subChannel=&tableName=studyaction&tableId=table_110&date=&day=&pageSize=1&pageNo=0&sourceType=0,1,2,3,4,5&IsRoll=0,1",
        "sliderUrl":
        "http://roll.qiushi.chinaso.com/newsQuery/query/getNewsList.htm?channel=&queryId=330&subChannel=&tableName=video&tableId=table_27&date=&day=&pageSize=4&pageNo=0&sourceType=0,1,2,3,4,5&IsRoll=0,1"
    },
    "热搜榜":
    [
     {
     "key":
     "廉洁自律准则"
     },
     {
     "key":
     "三严三实"
     },
     {
     "key":
     "纪律处分条例"
     },
     {
     "key":
     "关键少数"
     },
     {
     "key":
     "“两学一做”学习常态化"
     },
     {
     "key":
     "全面从严治党"
     },
     {
     "key":
     "孔繁森"
     },
     {
     "key":
     "焦裕禄"
     }
     ],
    "资料":
    {
        "allUrl":
        "http://roll.qiushi.chinaso.com/newsQuery/query/getNewsList.htm?channel=&queryId=348,350,352,354&subChannel=&tableName=studyaction&tableId=table_110&date=&day=&pageSize=20&type=abstract&sourceType=0,1,2,3,4,5&IsRoll=0,1",
        "党代会":
        "http://roll.qiushi.chinaso.com/newsQuery/query/getNewsList.htm?channel=&queryId=352&subChannel=&tableName=studyaction&tableId=table_110&date=&day=&pageSize=20&type=abstract&sourceType=0,1,2,3,4,5&IsRoll=0,1",
        "经典著作":
        "http://roll.qiushi.chinaso.com/newsQuery/query/getNewsList.htm?channel=&queryId=354&subChannel=&tableName=studyaction&tableId=table_110&date=&day=&pageSize=20&type=abstract&sourceType=0,1,2,3,4,5&IsRoll=0,1",
        "重要文章":
        "http://roll.qiushi.chinaso.com/newsQuery/query/getNewsList.htm?channel=&queryId=348&subChannel=&tableName=studyaction&tableId=table_110&date=&day=&pageSize=20&type=abstract&sourceType=0,1,2,3,4,5&IsRoll=0,1",
        "领导人报道":
        "http://roll.qiushi.chinaso.com/newsQuery/query/getNewsList.htm?channel=&queryId=350&subChannel=&tableName=studyaction&tableId=table_110&date=&day=&pageSize=20&type=abstract&sourceType=0,1,2,3,4,5&IsRoll=0,1"
    },
    "首页":
    [
     {
     "id":
     "0001",
     "listUrl":
     "http://roll.qiushi.chinaso.com/newsQuery/query/getNewsList.htm?channel=&queryId=292&subChannel=&tableName=studyaction&tableId=table_110&date=&day=&pageSize=20&type=abstract&sourceType=0,1,2,3,4,5&IsRoll=0,1",
     "lock":
     true,
     "name":
     "推荐",
     "show":
     true,
     "sliderUrl":
     "http://roll.qiushi.chinaso.com/newsQuery/query/getNewsList.htm?channel=&queryId=290&subChannel=&tableName=studyaction&tableId=table_110&date=&day=&pageSize=4&pageNo=0&sourceType=0,1,2,3,4,5&IsRoll=0,1"
     },
     {
     "id":
     "10001",
     "listUrl":
     "http://roll.qiushi.chinaso.com/newsQuery/query/getNewsList.htm?channel=&queryId=292&subChannel=&tableName=studyaction&tableId=table_110&date=&day=&pageSize=20&type=abstract&sourceType=0,1,2,3,4,5&IsRoll=0,1",
     "lock":
     true,
     "name":
     "推荐4",
     "show":
     true,
     "sliderUrl":
     "http://roll.qiushi.chinaso.com/newsQuery/query/getNewsList.htm?channel=&queryId=290&subChannel=&tableName=studyaction&tableId=table_110&date=&day=&pageSize=4&pageNo=0&sourceType=0,1,2,3,4,5&IsRoll=0,1"
     },
     {
     "id":
     "0002",
     "listUrl":
     "http://roll.qiushi.chinaso.com/newsQuery/query/getNewsList.htm?channel=&queryId=312&subChannel=&tableName=studyaction&tableId=table_110&date=&day=&pageSize=20&type=abstract&sourceType=0,1,2,3,4,5&IsRoll=0,1",
     "lock":
     false,
     "name":
     "习近平",
     "show":
     true
     },
     {
     "id":
     "0003",
     "listUrl":
     "http://roll.qiushi.chinaso.com/newsQuery/query/getNewsList.htm?channel=&queryId=316&subChannel=&tableName=studyaction&tableId=table_110&date=&day=&pageSize=20&type=abstract&sourceType=0,1,2,3,4,5&IsRoll=0,1",
     "lock":
     false,
     "name":
     "理论",
     "show":
     true
     },
     {
     "id":
     "0004",
     "listUrl":
     "http://roll.qiushi.chinaso.com/newsQuery/query/getNewsList.htm?channel=&queryId=320&subChannel=&tableName=studyaction&tableId=table_110&date=&day=&pageSize=20&type=abstract&sourceType=0,1,2,3,4,5&IsRoll=0,1",
     "lock":
     false,
     "name":
     "实践",
     "show":
     true
     },
     {
     "id":
     "0005",
     "listUrl":
     "http://roll.qiushi.chinaso.com/newsQuery/query/getNewsList.htm?channel=&queryId=324&subChannel=&tableName=studyaction&tableId=table_110&date=&day=&pageSize=20&type=abstract&sourceType=0,1,2,3,4,5&IsRoll=0,1",
     "lock":
     false,
     "name":
     "先锋",
     "show":
     true
     },
     {
     "id":
     "0006",
     "listUrl":
     "http://roll.qiushi.chinaso.com/newsQuery/query/getNewsList.htm?channel=&queryId=328&subChannel=&tableName=studyaction&tableId=table_110&date=&day=&pageSize=20&type=abstract&sourceType=0,1,2,3,4,5&IsRoll=0,1",
     "lock":
     false,
     "name":
     "党章",
     "show":
     true
     },
     {
     "id":
     "0007",
     "listUrl":
     "http://roll.qiushi.chinaso.com/newsQuery/query/getNewsList.htm?channel=&queryId=302&subChannel=&tableName=studyaction&tableId=table_110&date=&day=&pageSize=20&type=abstract&sourceType=0,1,2,3,4,5&IsRoll=0,1",
     "lock":
     false,
     "name":
     "**频道",
     "show":
     true
     }
     ]
}
